MarketTime/__init__.py
MarketTime/future_market_time.py
MarketTime/market_time.py
MarketTime/stock_market_time.py
markettime-1.1.3.dist-info/licenses/LICENSE
markettime-1.1.3.dist-info/METADATA
markettime-1.1.3.dist-info/WHEEL
markettime-1.1.3.dist-info/top_level.txt
markettime-1.1.3.dist-info/RECORD
