Metadata-Version: 2.4
Name: MarketTime
Version: 1.1.3
Summary: This is a tool to check the time in the market
Home-page: https://github.com/Liaou3/MarketTime
Download-URL: 
Author: VincentLiao
Author-email: vincent932693@gmail.com
License: GPLv3
Requires-Python: >=3.10
License-File: LICENSE
Dynamic: author
Dynamic: author-email
Dynamic: description
Dynamic: description-content-type
Dynamic: home-page
Dynamic: license
Dynamic: license-file
Dynamic: requires-python
Dynamic: summary
